visionpluspython/__init__.py
visionpluspython/auth.py
visionpluspython/client.py
visionpluspython/const.py
visionpluspython/exceptions.py
visionpluspython/models.py
visionpluspython-1.0.1.dist-info/licenses/LICENSE
visionpluspython-1.0.1.dist-info/METADATA
visionpluspython-1.0.1.dist-info/WHEEL
visionpluspython-1.0.1.dist-info/top_level.txt
visionpluspython-1.0.1.dist-info/RECORD
