Metadata-Version: 2.4
Name: visionpluspython
Version: 1.0.1
Summary: Python API wrapper for Watts Vision+ smart heating system
Author-email: Théo BRILLAND <theo.brilland@wattswater.com>, Devender VERMA <devender.verma@wattswater.com>, Seweryn SIREK <ssi@spyro-soft.com>
License: MIT
Project-URL: Homepage, https://github.com/Watts-Digital/visionpluspython
Project-URL: Documentation, https://github.com/Watts-Digital/visionpluspython
Project-URL: Repository, https://github.com/Watts-Digital/visionpluspython
Project-URL: Bug Tracker, https://github.com/Watts-Digital/visionpluspython/issues
Project-URL: Changelog, https://github.com/Watts-Digital/visionpluspython/blob/main/CHANGELOG.md
Keywords: watts,vision,plus,smart,heating,thermostat,home automation,iot
Classifier: Intended Audience :: Developers
Classifier: License :: OSI Approved :: MIT License
Classifier: Operating System :: OS Independent
Classifier: Programming Language :: Python :: 3
Classifier: Topic :: Home Automation
Requires-Python: >=3.9
License-File: LICENSE
Requires-Dist: aiohttp<4.0.0,>=3.8.0
Provides-Extra: dev
Requires-Dist: pytest>=7.0.0; extra == "dev"
Requires-Dist: pytest-asyncio>=0.21.0; extra == "dev"
Requires-Dist: pytest-cov>=4.0.0; extra == "dev"
Requires-Dist: mypy>=1.0.0; extra == "dev"
Requires-Dist: twine>=4.0.0; extra == "dev"
Requires-Dist: build>=0.10.0; extra == "dev"
Dynamic: license-file
